{
  "name": "Items in a Port Master’s Office",
  "maxItems": 5,
  "items": [
    { "name": "Shipping Manifesto", "rarity": "common" },
    { "name": "Maps of Surrounding Seas", "rarity": "common" },
    { "name": "Inkwell (dry)", "rarity": "common" },
    { "name": "Bowl of Fish Eggs", "rarity": "common" },
    { "name": "Decorative Helm", "rarity": "uncommon" },
    { "name": "List of Ships Arriving Today", "rarity": "common" },
    { "name": "Warning Letter to Pirate Captain", "rarity": "rare" },
    { "name": "Fishing Rod", "rarity": "common" },
    { "name": "Prayers to Sea God", "rarity": "common" },
    { "name": "Candles (1d4)", "rarity": "common" },
    { "name": "Mounted Shark", "rarity": "uncommon" },
    { "name": "Bounty Board", "rarity": "uncommon" },
    { "name": "Ship’s Flag", "rarity": "common" },
    { "name": "Jeweled Seashell", "rarity": "rare" },
    { "name": "Sea Chest", "rarity": "common" },
    { "name": "Legal Documents", "rarity": "uncommon" },
    { "name": "Port Master’s Seal", "rarity": "uncommon" },
    { "name": "Bottles Of Mead (1D8)", "rarity": "common" },
    { "name": "Pewter Flagon (empty)", "rarity": "common" },
    { "name": "Visitors Ledger", "rarity": "common" },
    { "name": "Star Charts", "rarity": "uncommon" },
    { "name": "Calendar", "rarity": "common" },
    { "name": "Decorative Oar", "rarity": "common" },
    { "name": "The Art of Sea Navigation (book)", "rarity": "uncommon" },
    { "name": "Fiddle", "rarity": "common" },
    { "name": "Fancy Lockbox", "rarity": "uncommon" },
    { "name": "Ferry Schedules", "rarity": "common" },
    { "name": "List of Local Ships", "rarity": "common" },
    { "name": "Port Master’s Journal", "rarity": "uncommon" },
    { "name": "Keys (1D12)", "rarity": "uncommon" },
    { "name": "Quills (1D4)", "rarity": "common" },
    { "name": "Model Ship", "rarity": "uncommon" },
    { "name": "Sextant", "rarity": "uncommon" },
    { "name": "Antique Sword", "rarity": "uncommon" },
    { "name": "Small Vault", "rarity": "uncommon" },
    { "name": "Mounted Crab", "rarity": "common" },
    { "name": "Tax Records", "rarity": "uncommon" },
    { "name": "Map of Shipping Route", "rarity": "common" },
    { "name": "Old Shipping Records", "rarity": "common" },
    { "name": "Warehouse Inventory Log", "rarity": "common" },
    { "name": "Wax (5 cubes)", "rarity": "common" },
    { "name": "Symbol of Sea God", "rarity": "uncommon" },
    { "name": "Rusted Lockbox", "rarity": "common" },
    { "name": "Pipe Tobacco", "rarity": "common" },
    { "name": "Bucket of Seashells", "rarity": "common" },
    { "name": "Inkwell", "rarity": "common" },
    { "name": "Conch Shell", "rarity": "common" },
    { "name": "Help Wanted Ad", "rarity": "common" },
    { "name": "Compass", "rarity": "uncommon" },
    { "name": "Donation Box for Families of Lost Sailors", "rarity": "common" },
    { "name": "Map Of Town (Plastered On Wall)", "rarity": "common" },
    { "name": "Illustration of Legendary Ship", "rarity": "uncommon" },
    { "name": "Collection of Beautiful Seashells", "rarity": "uncommon" },
    { "name": "List of Common Sea Laws", "rarity": "common" },
    { "name": "Single Key", "rarity": "uncommon" },
    { "name": "Bookshelves (1D100 books)", "rarity": "uncommon" },
    { "name": "Mounted Swordfish", "rarity": "uncommon" },
    { "name": "Lamp Oil (2 flasks)", "rarity": "common" },
    { "name": "Rum (1D12 bottles)", "rarity": "common" },
    { "name": "Bundle of Letters", "rarity": "common" },
    { "name": "Antique Fishing Gear", "rarity": "uncommon" },
    { "name": "Memorial Plaque to Lost Sailors", "rarity": "uncommon" },
    { "name": "Jar Of Marbles", "rarity": "common" },
    { "name": "Stuffed Squid", "rarity": "uncommon" },
    { "name": "Jar Of Pickled Fish", "rarity": "common" },
    { "name": "Ship In Bottle", "rarity": "uncommon" },
    { "name": "Antique Anchor", "rarity": "uncommon" },
    { "name": "Map of the Port and Related Areas", "rarity": "common" },
    { "name": "Financial Reports", "rarity": "uncommon" },
    { "name": "Trading Company Contract", "rarity": "uncommon" },
    { "name": "A Letter to the Cooper", "rarity": "common" },
    { "name": "Dagger", "rarity": "common" },
    { "name": "Weatherworn Captain’s Cloak", "rarity": "common" },
    { "name": "Old Captain’s Journal", "rarity": "uncommon" },
    { "name": "Wanted Posters Marked “Collected”", "rarity": "uncommon" },
    { "name": "Pirate Flag", "rarity": "uncommon" },
    { "name": "Straight Razor", "rarity": "common" },
    { "name": "Dried Rations (1D4)", "rarity": "common" },
    { "name": "Spyglass", "rarity": "uncommon" },
    { "name": "Manual on Knot Tying", "rarity": "common" },
    { "name": "Treasure Map", "rarity": "rare" },
    { "name": "Gold Pieces (1D20)", "rarity": "uncommon" },
    { "name": "Short Sword", "rarity": "common" },
    { "name": "Coat Of Arms", "rarity": "uncommon" },
    { "name": "Weird Symbols Scratched on Wall", "rarity": "uncommon" },
    { "name": "Book of Sea Shanties", "rarity": "common" },
    { "name": "Bill of Sale for a Ship", "rarity": "uncommon" },
    { "name": "Rabbit’s Foot", "rarity": "common" },
    { "name": "Alter to Sea God", "rarity": "uncommon" },
    { "name": "Dragon Skull", "rarity": "very_rare" },
    { "name": "Strange Creatures of the Deep (book)", "rarity": "rare" },
    { "name": "Silver Pieces (1D100)", "rarity": "uncommon" },
    { "name": "List of Port Rules", "rarity": "common" },
    { "name": "Pouch Filled with Shark’s Teeth", "rarity": "common" },
    { "name": "Hourglass", "rarity": "uncommon" },
    { "name": "Preserved Tentacle (35ft)", "rarity": "very_rare" },
    { "name": "Vellum (1d12 sheets)", "rarity": "common" },
    { "name": "Mystical Seashell", "rarity": "very_rare" },
    { "name": "Skull of Pirate", "rarity": "uncommon" },
    { "name": "Egg (decorative, 2ft tall)", "rarity": "uncommon" }
  ]
}