{
  "name": "Items in a Noble’s Bedchamber",
  "maxItems": 5,
  "items": [
    { "name": "Family sword", "rarity": "uncommon" },
    { "name": "Sapphire ring", "rarity": "rare" },
    { "name": "Chamber pot", "rarity": "common" },
    { "name": "Family Crest", "rarity": "uncommon" },
    { "name": "Suit of Armor", "rarity": "rare" },
    { "name": "Portrait of Ancestor", "rarity": "uncommon" },
    { "name": "Signet ring", "rarity": "uncommon" },
    { "name": "Ornate chest", "rarity": "uncommon" },
    { "name": "Large wardrobe", "rarity": "common" },
    { "name": "Emerald ring", "rarity": "rare" },
    { "name": "Locked door", "rarity": "common" },
    { "name": "Mounted fish", "rarity": "common" },
    { "name": "Stuffed Minotaur", "rarity": "very_rare" },
    { "name": "Inkwell", "rarity": "common" },
    { "name": "Lavish chair", "rarity": "uncommon" },
    { "name": "Combination to safe", "rarity": "uncommon" },
    { "name": "Self portrait", "rarity": "uncommon" },
    { "name": "Undergarments", "rarity": "common" },
    { "name": "Silk pantaloons", "rarity": "uncommon" },
    { "name": "Silver Urn", "rarity": "uncommon" },
    { "name": "Painting of noble lineage", "rarity": "rare" },
    { "name": "Map of local area", "rarity": "uncommon" },
    { "name": "Shelf of hunting trophies", "rarity": "uncommon" },
    { "name": "Noble’s Journal", "rarity": "uncommon" },
    { "name": "Gold statuette", "rarity": "uncommon" },
    { "name": "Decorative Axe", "rarity": "uncommon" },
    { "name": "Large Ruby", "rarity": "very_rare" },
    { "name": "Stuffed falcon", "rarity": "uncommon" },
    { "name": "Bundle of love letters", "rarity": "common" },
    { "name": "Platter of exotic fruits", "rarity": "uncommon" },
    { "name": "Small safe", "rarity": "uncommon" },
    { "name": "Silver bathtub", "rarity": "uncommon" },
    { "name": "Burning letters", "rarity": "uncommon" },
    { "name": "Large bed with curtains", "rarity": "uncommon" },
    { "name": "Family Shield", "rarity": "uncommon" },
    { "name": "Painting of noble’s home", "rarity": "uncommon" },
    { "name": "Diamond ring", "rarity": "rare" },
    { "name": "Painting of beautiful woman", "rarity": "uncommon" },
    { "name": "Gold urn", "rarity": "uncommon" },
    { "name": "Stuffed wolf", "rarity": "uncommon" },
    { "name": "Large Emerald", "rarity": "very_rare" },
    { "name": "Gold trimmed desk", "rarity": "uncommon" },
    { "name": "Leather bindings", "rarity": "common" },
    { "name": "Unopened letter", "rarity": "common" },
    { "name": "Silver trimmed robes", "rarity": "uncommon" },
    { "name": "Model ship", "rarity": "uncommon" },
    { "name": "Gold trimmed fan", "rarity": "uncommon" },
    { "name": "Exquisite rug", "rarity": "uncommon" },
    { "name": "Painting easel", "rarity": "common" },
    { "name": "Mortar and pestle", "rarity": "common" },
    { "name": "Gold animal skull", "rarity": "uncommon" },
    { "name": "Silver trimmed fan", "rarity": "uncommon" },
    { "name": "Bottle of rare liquor", "rarity": "uncommon" },
    { "name": "Coin purse", "rarity": "common" },
    { "name": "Silver Locket", "rarity": "uncommon" },
    { "name": "Decorative armor", "rarity": "uncommon" },
    { "name": "Family axe", "rarity": "uncommon" },
    { "name": "Scepter", "rarity": "rare" },
    { "name": "Silver rose", "rarity": "uncommon" },
    { "name": "Bookshelf of family lineage", "rarity": "uncommon" },
    { "name": "Ancestor’s spear", "rarity": "uncommon" },
    { "name": "Exquisite vase", "rarity": "uncommon" },
    { "name": "Statue of noble", "rarity": "uncommon" },
    { "name": "Pearl necklace", "rarity": "rare" },
    { "name": "Gold bathtub", "rarity": "rare" },
    { "name": "Confiscated journal", "rarity": "uncommon" },
    { "name": "Painting of dragon", "rarity": "uncommon" },
    { "name": "Gold lion statuette", "rarity": "uncommon" },
    { "name": "Shrine to a God", "rarity": "uncommon" },
    { "name": "Map of neighboring city", "rarity": "uncommon" },
    { "name": "List of “rivals”", "rarity": "uncommon" },
    { "name": "Plan to usurp", "rarity": "rare" },
    { "name": "Large sapphire", "rarity": "very_rare" },
    { "name": "Ruby ring", "rarity": "rare" },
    { "name": "Gold locket", "rarity": "uncommon" },
    { "name": "Embroidered pajamas", "rarity": "uncommon" },
    { "name": "Expensive wine", "rarity": "uncommon" },
    { "name": "Golden rose", "rarity": "uncommon" },
    { "name": "Wedding attire", "rarity": "uncommon" },
    { "name": "Gold trimmed clothing", "rarity": "uncommon" },
    { "name": "Decorative sword", "rarity": "uncommon" },
    { "name": "Hidden Vault", "rarity": "very_rare" },
    { "name": "Mounted deer head", "rarity": "common" },
    { "name": "Alchemical notes", "rarity": "rare" },
    { "name": "Enchanted ring", "rarity": "very_rare" },
    { "name": "Slippers", "rarity": "common" },
    { "name": "Door to balcony", "rarity": "common" },
    { "name": "Caged falcon", "rarity": "uncommon" },
    { "name": "Hunting bow", "rarity": "common" },
    { "name": "Golden dragon skull (ruby eyes)", "rarity": "very_rare" },
    { "name": "Statue of ancestor", "rarity": "uncommon" },
    { "name": "Jewelry chest", "rarity": "uncommon" },
    { "name": "Large safe", "rarity": "uncommon" },
    { "name": "Discarded clothing", "rarity": "common" },
    { "name": "Ancestral Sword", "rarity": "uncommon" },
    { "name": "Shrine to ancestors", "rarity": "uncommon" },
    { "name": "Key to vault", "rarity": "rare" },
    { "name": "Assassin", "rarity": "rare" },
    { "name": "Silver dragon skull (sapphire eyes)", "rarity": "very_rare" },
    { "name": "Noble’s corpse", "rarity": "uncommon" }
  ]
}